LICENSE
MANIFEST.in
README.rst
setup.py
drda/__init__.py
drda/codepoint.py
drda/connection.py
drda/consts.py
drda/cursor.py
drda/ddm.py
drda/secmec9.py
drda/utils.py
pydrda.egg-info/PKG-INFO
pydrda.egg-info/SOURCES.txt
pydrda.egg-info/dependency_links.txt
pydrda.egg-info/requires.txt
pydrda.egg-info/top_level.txt