Metadata-Version: 2.1
Name: pydrda
Version: 0.5.0
Summary: DRDA protocol database driver
Home-page: https://github.com/nakagami/pydrda/
Author: Hajime Nakagami
Author-email: nakagami@gmail.com
License: MIT
Keywords: Db2,Apache Derby
Classifier: Development Status :: 4 - Beta
Classifier: License :: OSI Approved :: MIT License
Classifier: Operating System :: OS Independent
Classifier: Programming Language :: Python
Classifier: Programming Language :: Python :: 3
Classifier: Topic :: Database
License-File: LICENSE
